odoo10_addon_stock_warehouse_orderpoint_stock_info_unreserved-10.0.1.0.0.99.dev6-nspkg.pth
odoo/addons/stock_warehouse_orderpoint_stock_info_unreserved/README.rst
odoo/addons/stock_warehouse_orderpoint_stock_info_unreserved/__init__.py
odoo/addons/stock_warehouse_orderpoint_stock_info_unreserved/__manifest__.py
odoo/addons/stock_warehouse_orderpoint_stock_info_unreserved/i18n/ca.po
odoo/addons/stock_warehouse_orderpoint_stock_info_unreserved/i18n/cs_CZ.po
odoo/addons/stock_warehouse_orderpoint_stock_info_unreserved/i18n/de.po
odoo/addons/stock_warehouse_orderpoint_stock_info_unreserved/i18n/es.po
odoo/addons/stock_warehouse_orderpoint_stock_info_unreserved/i18n/es_ES.po
odoo/addons/stock_warehouse_orderpoint_stock_info_unreserved/i18n/fr.po
odoo/addons/stock_warehouse_orderpoint_stock_info_unreserved/i18n/hr.po
odoo/addons/stock_warehouse_orderpoint_stock_info_unreserved/i18n/pt_BR.po
odoo/addons/stock_warehouse_orderpoint_stock_info_unreserved/i18n/sl.po
odoo/addons/stock_warehouse_orderpoint_stock_info_unreserved/i18n/stock_warehouse_orderpoint_stock_info_unreserved.pot
odoo/addons/stock_warehouse_orderpoint_stock_info_unreserved/models/__init__.py
odoo/addons/stock_warehouse_orderpoint_stock_info_unreserved/models/stock_warehouse_orderpoint.py
odoo/addons/stock_warehouse_orderpoint_stock_info_unreserved/static/description/icon.png
odoo/addons/stock_warehouse_orderpoint_stock_info_unreserved/tests/__init__.py
odoo/addons/stock_warehouse_orderpoint_stock_info_unreserved/tests/test_stock_warehouse_orderpoint.py
odoo/addons/stock_warehouse_orderpoint_stock_info_unreserved/views/stock_warehouse_orderpoint_view.xml
odoo10_addon_stock_warehouse_orderpoint_stock_info_unreserved-10.0.1.0.0.99.dev6.dist-info/METADATA
odoo10_addon_stock_warehouse_orderpoint_stock_info_unreserved-10.0.1.0.0.99.dev6.dist-info/WHEEL
odoo10_addon_stock_warehouse_orderpoint_stock_info_unreserved-10.0.1.0.0.99.dev6.dist-info/namespace_packages.txt
odoo10_addon_stock_warehouse_orderpoint_stock_info_unreserved-10.0.1.0.0.99.dev6.dist-info/top_level.txt
odoo10_addon_stock_warehouse_orderpoint_stock_info_unreserved-10.0.1.0.0.99.dev6.dist-info/RECORD
