Metadata-Version: 2.1
Name: odoo10-addon-stock-warehouse-orderpoint-stock-info-unreserved
Version: 10.0.1.0.0.99.dev6
Summary: Stock Warehouse Orderpoint Stock Info Unreserved
Home-page: https://github.com/OCA/stock-logistics-warehouse
Author: Eficent, Odoo Community Association (OCA)
Author-email: support@odoo-community.org
License: AGPL-3
Platform: UNKNOWN
Classifier: Programming Language :: Python
Classifier: Framework :: Odoo
Classifier: License :: OSI Approved :: GNU Affero General Public License v3
Requires-Python: ~=2.7
Requires-Dist: odoo10-addon-stock-available-unreserved
Requires-Dist: odoo10-addon-stock-warehouse-orderpoint-stock-info
Requires-Dist: odoo (<10.1dev,>=10.0)
